README.txt
setup.py
FakeZopeInterface/__init__.py
FakeZopeInterface.egg-info/PKG-INFO
FakeZopeInterface.egg-info/SOURCES.txt
FakeZopeInterface.egg-info/dependency_links.txt
FakeZopeInterface.egg-info/entry_points.txt
FakeZopeInterface.egg-info/namespace_packages.txt
FakeZopeInterface.egg-info/not-zip-safe
FakeZopeInterface.egg-info/requires.txt
FakeZopeInterface.egg-info/top_level.txt
FakeZopeInterface/FakeZopeInterface/__init__.py
FakeZopeInterface/FakeZopeInterface/changes.txt
FakeZopeInterface/FakeZopeInterface/readme.txt